[
  {
    "mode": "ECB",
    "data_size_bytes": 1024,
    "data_size_label": "1 KB",
    "trials": 5,
    "enc_time_mean_s": 1.154e-05,
    "enc_time_stdev_s": 1.302e-05,
    "dec_time_mean_s": 6.62e-06,
    "dec_time_stdev_s": 2.83e-06,
    "enc_throughput_MBps": 84.6241,
    "dec_throughput_MBps": 147.5171
  },
  {
    "mode": "CBC",
    "data_size_bytes": 1024,
    "data_size_label": "1 KB",
    "trials": 5,
    "enc_time_mean_s": 1.422e-05,
    "enc_time_stdev_s": 1.366e-05,
    "dec_time_mean_s": 9.56e-06,
    "dec_time_stdev_s": 3.33e-06,
    "enc_throughput_MBps": 68.6753,
    "dec_throughput_MBps": 102.1509
  },
  {
    "mode": "CTR",
    "data_size_bytes": 1024,
    "data_size_label": "1 KB",
    "trials": 5,
    "enc_time_mean_s": 1.15e-05,
    "enc_time_stdev_s": 9.29e-06,
    "dec_time_mean_s": 7.64e-06,
    "dec_time_stdev_s": 2.18e-06,
    "enc_throughput_MBps": 84.9185,
    "dec_throughput_MBps": 127.8223
  },
  {
    "mode": "GCM",
    "data_size_bytes": 1024,
    "data_size_label": "1 KB",
    "trials": 5,
    "enc_time_mean_s": 3.908e-05,
    "enc_time_stdev_s": 1.308e-05,
    "dec_time_mean_s": 4.204e-05,
    "dec_time_stdev_s": 5.86e-06,
    "enc_throughput_MBps": 24.9888,
    "dec_throughput_MBps": 23.2294
  },
  {
    "mode": "ECB",
    "data_size_bytes": 10240,
    "data_size_label": "10 KB",
    "trials": 5,
    "enc_time_mean_s": 1.412e-05,
    "enc_time_stdev_s": 1.656e-05,
    "dec_time_mean_s": 7.86e-06,
    "dec_time_stdev_s": 2.65e-06,
    "enc_throughput_MBps": 691.6165,
    "dec_throughput_MBps": 1242.4461
  },
  {
    "mode": "CBC",
    "data_size_bytes": 10240,
    "data_size_label": "10 KB",
    "trials": 5,
    "enc_time_mean_s": 2.538e-05,
    "enc_time_stdev_s": 1.447e-05,
    "dec_time_mean_s": 2.094e-05,
    "dec_time_stdev_s": 2.84e-06,
    "enc_throughput_MBps": 384.7764,
    "dec_throughput_MBps": 466.3622
  },
  {
    "mode": "CTR",
    "data_size_bytes": 10240,
    "data_size_label": "10 KB",
    "trials": 5,
    "enc_time_mean_s": 1.932e-05,
    "enc_time_stdev_s": 2.2e-05,
    "dec_time_mean_s": 1.072e-05,
    "dec_time_stdev_s": 3.75e-06,
    "enc_throughput_MBps": 505.467,
    "dec_throughput_MBps": 910.9727
  },
  {
    "mode": "GCM",
    "data_size_bytes": 10240,
    "data_size_label": "10 KB",
    "trials": 5,
    "enc_time_mean_s": 7.478e-05,
    "enc_time_stdev_s": 8.372e-05,
    "dec_time_mean_s": 5.188e-05,
    "dec_time_stdev_s": 1.641e-05,
    "enc_throughput_MBps": 130.5914,
    "dec_throughput_MBps": 188.2349
  },
  {
    "mode": "ECB",
    "data_size_bytes": 102400,
    "data_size_label": "100 KB",
    "trials": 5,
    "enc_time_mean_s": 3.732e-05,
    "enc_time_stdev_s": 2.245e-05,
    "dec_time_mean_s": 2.976e-05,
    "dec_time_stdev_s": 1.005e-05,
    "enc_throughput_MBps": 2616.7268,
    "dec_throughput_MBps": 3281.4607
  },
  {
    "mode": "CBC",
    "data_size_bytes": 102400,
    "data_size_label": "100 KB",
    "trials": 5,
    "enc_time_mean_s": 0.0002364,
    "enc_time_stdev_s": 7.854e-05,
    "dec_time_mean_s": 0.0002061,
    "dec_time_stdev_s": 5.486e-05,
    "enc_throughput_MBps": 413.0975,
    "dec_throughput_MBps": 473.8295
  },
  {
    "mode": "CTR",
    "data_size_bytes": 102400,
    "data_size_label": "100 KB",
    "trials": 5,
    "enc_time_mean_s": 3.928e-05,
    "enc_time_stdev_s": 1.522e-05,
    "dec_time_mean_s": 3.382e-05,
    "dec_time_stdev_s": 7.02e-06,
    "enc_throughput_MBps": 2486.1571,
    "dec_throughput_MBps": 2887.5297
  },
  {
    "mode": "GCM",
    "data_size_bytes": 102400,
    "data_size_label": "100 KB",
    "trials": 5,
    "enc_time_mean_s": 7.926e-05,
    "enc_time_stdev_s": 2.34e-05,
    "dec_time_mean_s": 7.32e-05,
    "dec_time_stdev_s": 9.58e-06,
    "enc_throughput_MBps": 1232.1001,
    "dec_throughput_MBps": 1334.1017
  },
  {
    "mode": "ECB",
    "data_size_bytes": 1048576,
    "data_size_label": "1 MB",
    "trials": 5,
    "enc_time_mean_s": 0.00097506,
    "enc_time_stdev_s": 8.242e-05,
    "dec_time_mean_s": 0.00098638,
    "dec_time_stdev_s": 0.00017048,
    "enc_throughput_MBps": 1025.5779,
    "dec_throughput_MBps": 1013.8081
  },
  {
    "mode": "CBC",
    "data_size_bytes": 1048576,
    "data_size_label": "1 MB",
    "trials": 5,
    "enc_time_mean_s": 0.0020325,
    "enc_time_stdev_s": 6.052e-05,
    "dec_time_mean_s": 0.00210878,
    "dec_time_stdev_s": 3.768e-05,
    "enc_throughput_MBps": 492.0049,
    "dec_throughput_MBps": 474.2078
  },
  {
    "mode": "CTR",
    "data_size_bytes": 1048576,
    "data_size_label": "1 MB",
    "trials": 5,
    "enc_time_mean_s": 0.00077894,
    "enc_time_stdev_s": 0.00010409,
    "dec_time_mean_s": 0.00079388,
    "dec_time_stdev_s": 9.925e-05,
    "enc_throughput_MBps": 1283.7959,
    "dec_throughput_MBps": 1259.6362
  },
  {
    "mode": "GCM",
    "data_size_bytes": 1048576,
    "data_size_label": "1 MB",
    "trials": 5,
    "enc_time_mean_s": 0.00091454,
    "enc_time_stdev_s": 0.00013274,
    "dec_time_mean_s": 0.00089632,
    "dec_time_stdev_s": 0.00013207,
    "enc_throughput_MBps": 1093.4459,
    "dec_throughput_MBps": 1115.673
  }
]